plantvarfilter/__init__.py
plantvarfilter/annotation_utils.py
plantvarfilter/batch_gwas.py
plantvarfilter/bcftools_utils.py
plantvarfilter/bigfile_handler.py
plantvarfilter/genomic_prediction_pipeline.py
plantvarfilter/gwas_AI_model.py
plantvarfilter/gwas_pipeline.py
plantvarfilter/helpers.py
plantvarfilter/ld_utils.py
plantvarfilter/main_ui.py
plantvarfilter/pangenome_builder.py
plantvarfilter/pipeline_plots.py
plantvarfilter/samtools_utils.py
plantvarfilter/variant_caller_utils.py
plantvarfilter/vcf_quality.py
plantvarfilter/assets/000111.png
plantvarfilter/assets/1.png
plantvarfilter/assets/10.png
plantvarfilter/assets/11.png
plantvarfilter/assets/12.png
plantvarfilter/assets/123123.png
plantvarfilter/assets/13.png
plantvarfilter/assets/14.png
plantvarfilter/assets/15.png
plantvarfilter/assets/16.png
plantvarfilter/assets/17.png
plantvarfilter/assets/18.png
plantvarfilter/assets/19.png
plantvarfilter/assets/2.png
plantvarfilter/assets/20.png
plantvarfilter/assets/21.png
plantvarfilter/assets/22.png
plantvarfilter/assets/222.png
plantvarfilter/assets/23.png
plantvarfilter/assets/24.png
plantvarfilter/assets/25.png
plantvarfilter/assets/26.png
plantvarfilter/assets/27.png
plantvarfilter/assets/28.png
plantvarfilter/assets/29.png
plantvarfilter/assets/3.png
plantvarfilter/assets/30.png
plantvarfilter/assets/31.png
plantvarfilter/assets/32.png
plantvarfilter/assets/3352623.png
plantvarfilter/assets/4.png
plantvarfilter/assets/5.png
plantvarfilter/assets/6.png
plantvarfilter/assets/678678.png
plantvarfilter/assets/7.png
plantvarfilter/assets/8.png
plantvarfilter/assets/9.png
plantvarfilter/assets/gui_overview.png
plantvarfilter/assets/gwas_results.csv
plantvarfilter/assets/gwas_results_top10000.csv
plantvarfilter/assets/log.txt
plantvarfilter/assets/logo.png
plantvarfilter/assets/logo_lab.png
plantvarfilter/assets/manhatten_plot_high.png
plantvarfilter/assets/plantvarfilter.png
plantvarfilter/assets/qq_plot_high.png
plantvarfilter/assets/fonts/test.ttf
plantvarfilter-0.2.12.dist-info/METADATA
plantvarfilter-0.2.12.dist-info/WHEEL
plantvarfilter-0.2.12.dist-info/entry_points.txt
plantvarfilter-0.2.12.dist-info/top_level.txt
plantvarfilter-0.2.12.dist-info/RECORD
