Metadata-Version: 2.4
Name: plantvarfilter
Version: 0.2.12
Summary: Integrated GWAS and genomic prediction pipeline with a GUI for plant genomics.
Author-email: "Ahmed Yassin, Computational Biologist" <ahmedyassin300@outlook.com>, "Falak Sher Khan, Post-doctoral scientist" <falak.khan@pku.edu.cn>
License: MIT
Project-URL: Homepage, https://github.com/AHMEDY3DGENOME/PlantVarFilter
Project-URL: Documentation, https://github.com/AHMEDY3DGENOME/PlantVarFilter/wiki
Project-URL: Issue Tracker, https://github.com/AHMEDY3DGENOME/PlantVarFilter/issues
Keywords: GWAS,genomics,plants,bioinformatics,variant-calling,machine-learning
Requires-Python: >=3.10
Requires-Dist: numpy>=1.26
Requires-Dist: pandas>=2.0
Requires-Dist: scipy>=1.11
Requires-Dist: matplotlib>=3.7
Requires-Dist: scikit-learn>=1.3
Requires-Dist: dearpygui>=1.11
Provides-Extra: ml
Requires-Dist: xgboost>=2.0; extra == "ml"
Provides-Extra: gwas
Requires-Dist: fastlmm; python_version < "3.12" and extra == "gwas"
Requires-Dist: pysnptools; extra == "gwas"
Requires-Dist: geneview; extra == "gwas"
Provides-Extra: all
Requires-Dist: xgboost>=2.0; extra == "all"
Requires-Dist: fastlmm; python_version < "3.12" and extra == "all"
Requires-Dist: pysnptools; extra == "all"
Requires-Dist: geneview; extra == "all"
